mcp_schema_server/__init__.py
mcp_schema_server/config.py
mcp_schema_server/server.py
mcp_schema_server/db/__init__.py
mcp_schema_server/db/connection.py
mcp_schema_server/tools/__init__.py
mcp_schema_server/tools/schema_tools.py
mcp_schema_server-0.2.0.dist-info/METADATA
mcp_schema_server-0.2.0.dist-info/WHEEL
mcp_schema_server-0.2.0.dist-info/entry_points.txt
mcp_schema_server-0.2.0.dist-info/licenses/LICENSE
mcp_schema_server-0.2.0.dist-info/RECORD
