Metadata-Version: 2.4
Name: mcp-schema-server
Version: 0.2.0
Summary: MCP server with schema-only query tools for MySQL databases
Author: N8_P
License: MIT
License-File: LICENSE
Keywords: database,mcp,mysql,schema
Classifier: Development Status :: 3 - Alpha
Classifier: Intended Audience :: Developers
Classifier: License :: OSI Approved :: MIT License
Classifier: Programming Language :: Python :: 3
Classifier: Programming Language :: Python :: 3.10
Classifier: Programming Language :: Python :: 3.11
Classifier: Programming Language :: Python :: 3.12
Requires-Python: >=3.10
Requires-Dist: mcp
Requires-Dist: pymysql
Requires-Dist: python-dotenv
Provides-Extra: dev
Requires-Dist: black; extra == 'dev'
Requires-Dist: mypy; extra == 'dev'
Requires-Dist: pytest; extra == 'dev'
Requires-Dist: pytest-asyncio; extra == 'dev'
Requires-Dist: ruff; extra == 'dev'
